odoo/addons/shopinvader_partner_vat/README.rst
odoo/addons/shopinvader_partner_vat/__init__.py
odoo/addons/shopinvader_partner_vat/__manifest__.py
odoo/addons/shopinvader_partner_vat/i18n/shopinvader_partner_vat.pot
odoo/addons/shopinvader_partner_vat/readme/CONTRIBUTORS.rst
odoo/addons/shopinvader_partner_vat/readme/DESCRIPTION.rst
odoo/addons/shopinvader_partner_vat/readme/INSTALLATION.rst
odoo/addons/shopinvader_partner_vat/services/__init__.py
odoo/addons/shopinvader_partner_vat/services/vat.py
odoo/addons/shopinvader_partner_vat/static/description/index.html
odoo/addons/shopinvader_partner_vat/tests/__init__.py
odoo/addons/shopinvader_partner_vat/tests/test_check_vat.py
odoo/addons/shopinvader_partner_vat/tests/cassettes/failure.json
odoo/addons/shopinvader_partner_vat/tests/cassettes/success.json
odoo14_addon_shopinvader_partner_vat-14.0.1.0.2.dist-info/METADATA
odoo14_addon_shopinvader_partner_vat-14.0.1.0.2.dist-info/WHEEL
odoo14_addon_shopinvader_partner_vat-14.0.1.0.2.dist-info/top_level.txt
odoo14_addon_shopinvader_partner_vat-14.0.1.0.2.dist-info/RECORD
